MANIFEST.in
README.rst
setup.py
collective/__init__.py
collective.geo.file.egg-info/PKG-INFO
collective.geo.file.egg-info/SOURCES.txt
collective.geo.file.egg-info/dependency_links.txt
collective.geo.file.egg-info/entry_points.txt
collective.geo.file.egg-info/namespace_packages.txt
collective.geo.file.egg-info/not-zip-safe
collective.geo.file.egg-info/requires.txt
collective.geo.file.egg-info/top_level.txt
collective/geo/__init__.py
collective/geo/file/README.txt
collective/geo/file/__init__.py
collective/geo/file/config.py
collective/geo/file/configure.zcml
collective/geo/file/interfaces.py
collective/geo/file/overrides.zcml
collective/geo/file/setuphandlers.py
collective/geo/file/tests.py
collective/geo/file/utils.py
collective/geo/file/version.txt
collective/geo/file/browser/__init__.py
collective/geo/file/browser/configure.zcml
collective/geo/file/browser/filekmlview.pt
collective/geo/file/browser/filekmlview.py
collective/geo/file/browser/kmlfiletopic_view.pt
collective/geo/file/browser/maplayer.py
collective/geo/file/locales/collective.geo.file.pot
collective/geo/file/locales/rebuild.sh
collective/geo/file/locales/es/LC_MESSAGES/collective.geo.file.po
collective/geo/file/profiles/default/browserlayer.xml
collective/geo/file/profiles/default/collective.geo.file-default.txt
collective/geo/file/profiles/default/metadata.xml
collective/geo/file/profiles/default/types/File.xml
docs/HISTORY.txt
docs/INSTALL.txt
docs/LICENSE.txt