Metadata-Version: 1.0
Name: collective.geo.file
Version: 0.6
Summary: An openlayers view for KML, KMZ and GPX files
Home-page: http://plone.org/products/collective.geo.file/
Author: Christian Ledermann
Author-email: christian.ledermann@gmail.com
License: GPL
Keywords: GIS KML KMZ Openlayers GPX
Platform: UNKNOWN
Classifier: Framework :: Plone
Classifier: Framework :: Plone :: 4.0
Classifier: Framework :: Plone :: 4.1
Classifier: Framework :: Plone :: 4.2
Classifier: Framework :: Plone :: 4.3
Classifier: Programming Language :: Python
Classifier: Topic :: Scientific/Engineering :: GIS
Classifier: License :: OSI Approved :: GNU General Public License (GPL)
